{
  "daddy_eagle": {
    "username": "daddy_eagle",
    "event": "December Ancients",
    "warlord": "B'alam Nak",
    "timestamp": "2025-11-29T00:48:09.187Z",
    "cardList": {
      "Character": {
        "B'alam Nak": 1,
        "Urnack": 1,
        "Nightmaster Rress": 1,
        "Joleg": 1,
        "B'haya, the Fiend": 1,
        "Jackals of Mourn": 3,
        "Nog, Pog, and Snivels": 3,
        "Yeg-Igryll's Altar": 1,
        "Archer Tower": 1,
        "Carg'rag": 3,
        "D'nath": 3,
        "Muddflek": 3,
        "FirRal": 3,
        "StartingArmy": {
          "B'alam Nak": 1,
          "Urnack": 1,
          "Nightmaster Rress": 1,
          "Joleg": 1,
          "B'haya, the Fiend": 1
        }
      },
      "Item": {
        "Portable Hole": 3,
        "Giant Bat": 2,
        "Nodwick": 1,
        "Farglass": 1,
        "Arbalest": 1,
        "StartingArmy": {}
      },
      "Action": {
        "Wither": 3,
        "Strain the Shot": 3,
        "Reconnaissance": 3,
        "Assassin's Strike": 2,
        "Meet at the Inn!": 3,
        "Crypt Wine": 3,
        "StartingArmy": {}
      }
    }
  },
  "daddy_eagle2": {
    "username": "daddy_eagle2",
    "event": "December Ancients+",
    "warlord": "Fo'ttr'ak'ka",
    "timestamp": "2025-11-29T02:37:53.287Z",
    "cardList": {
      "Character": {
        "Fo'ttr'ak'ka": 1,
        "Gunda": 2,
        "Nightmaster Rress": 1,
        "B'haya, the Fiend": 1,
        "Carg'rag": 3,
        "Yeg-Igryll's Altar": 1,
        "FirRal": 3,
        "Gush": 1,
        "Nemtok": 3,
        "SanUris": 3,
        "Lorik": 4,
        "Jackals of Mourn": 3,
        "StartingArmy": {
          "Fo'ttr'ak'ka": 1,
          "Gunda": 2,
          "Nightmaster Rress": 1,
          "B'haya, the Fiend": 1
        }
      },
      "Item": {
        "Black Moss": 3,
        "Destroyer's Armor": 3,
        "StartingArmy": {}
      },
      "Action": {
        "Final Blessing": 3,
        "Hero's Gambit": 3,
        "Incentives": 1,
        "Quick Strength": 3,
        "Rescue": 1,
        "Speed of the Falcon": 3,
        "Back Alley Tavern": 2,
        "Blind the Gods": 3,
        "StartingArmy": {}
      }
    }
  }
}